geci_test_tools/__init__.py
geci_test_tools/cli_tools.py
geci_test_tools/does_file_exist.py
geci_test_tools-0.2.0.dist-info/licenses/LICENSE
geci_test_tools-0.2.0.dist-info/WHEEL
geci_test_tools-0.2.0.dist-info/METADATA
geci_test_tools-0.2.0.dist-info/RECORD
