Metadata-Version: 2.4
Name: geci_test_tools
Version: 0.2.0
Summary: A module to run tests
Home-page: https://github.com/IslasGECI/test_tools
Author: Ciencia de Datos • GECI
Author-email: ciencia.datos@islas.org.mx
Requires-Python: >=3.9
Classifier: License :: OSI Approved :: GNU General Public License v3 or later (GPLv3+)
License-File: LICENSE
